jhadoo/__init__.py
jhadoo/__main__.py
jhadoo/cli.py
jhadoo/config.py
jhadoo/core.py
jhadoo/docker_tools.py
jhadoo/git_tools.py
jhadoo/notifications.py
jhadoo/restore.py
jhadoo/scheduler.py
jhadoo/telemetry.py
jhadoo/utils/__init__.py
jhadoo/utils/os_compat.py
jhadoo/utils/progress.py
jhadoo/utils/safety.py
jhadoo-1.2.1.dist-info/licenses/LICENSE
jhadoo-1.2.1.dist-info/METADATA
jhadoo-1.2.1.dist-info/WHEEL
jhadoo-1.2.1.dist-info/entry_points.txt
jhadoo-1.2.1.dist-info/top_level.txt
jhadoo-1.2.1.dist-info/RECORD
