Metadata-Version: 2.4
Name: jhadoo
Version: 1.2.1
Summary: Smart cleanup tool for developers - removes unused venv, node_modules, Docker images, scans Git repos, and more
Home-page: https://github.com/yourusername/jhadoo
Author: Bhavishya
Author-email: your.email@example.com
Project-URL: Bug Tracker, https://github.com/yourusername/jhadoo/issues
Project-URL: Documentation, https://github.com/yourusername/jhadoo#readme
Project-URL: Source Code, https://github.com/yourusername/jhadoo
Keywords: cleanup,disk-space,file-management,folder-cleanup,development-tools,build-cleanup,cache-cleanup,automation,devops,universal-cleaner,multi-language,folder-agnostic
Classifier: Development Status :: 4 - Beta
Classifier: Intended Audience :: Developers
Classifier: Topic :: System :: Filesystems
Classifier: Topic :: Utilities
Classifier: License :: OSI Approved :: MIT License
Classifier: Programming Language :: Python :: 3
Classifier: Programming Language :: Python :: 3.10
Classifier: Programming Language :: Python :: 3.11
Classifier: Programming Language :: Python :: 3.12
Classifier: Operating System :: OS Independent
Classifier: Operating System :: MacOS
Classifier: Operating System :: Microsoft :: Windows
Classifier: Operating System :: POSIX :: Linux
Requires-Python: >=3.10
License-File: LICENSE
Provides-Extra: notifications
Requires-Dist: win10toast>=0.9; platform_system == "Windows" and extra == "notifications"
Provides-Extra: dev
Requires-Dist: pytest>=7.0; extra == "dev"
Requires-Dist: pytest-cov>=4.0; extra == "dev"
Requires-Dist: black>=23.0; extra == "dev"
Requires-Dist: flake8>=6.0; extra == "dev"
Requires-Dist: mypy>=1.0; extra == "dev"
Dynamic: author
Dynamic: author-email
Dynamic: classifier
Dynamic: description
Dynamic: description-content-type
Dynamic: home-page
Dynamic: keywords
Dynamic: license-file
Dynamic: project-url
Dynamic: provides-extra
Dynamic: requires-python
Dynamic: summary
